<annotation>
	<folder>train</folder>
	<filename>pothole65.jpg</filename>
	<path>/home/amenor/seniorProject/potholedatasets/potholedatasetCompressed-1.21.21/train/pothole65.jpg</path>
	<source>
		<database>Unknown</database>
	</source>
	<size>
		<width>800</width>
		<height>600</height>
		<depth>3</depth>
	</size>
	<segmented>0</segmented>
	<object>
		<name>pothole</name>
		<pose>Unspecified</pose>
		<truncated>0</truncated>
		<difficult>0</difficult>
		<bndbox>
			<xmin>598</xmin>
			<ymin>437</ymin>
			<xmax>643</xmax>
			<ymax>465</ymax>
		</bndbox>
	</object>
	<object>
		<name>pothole</name>
		<pose>Unspecified</pose>
		<truncated>0</truncated>
		<difficult>0</difficult>
		<bndbox>
			<xmin>444</xmin>
			<ymin>233</ymin>
			<xmax>493</xmax>
			<ymax>257</ymax>
		</bndbox>
	</object>
	<object>
		<name>pothole</name>
		<pose>Unspecified</pose>
		<truncated>0</truncated>
		<difficult>0</difficult>
		<bndbox>
			<xmin>473</xmin>
			<ymin>270</ymin>
			<xmax>534</xmax>
			<ymax>310</ymax>
		</bndbox>
	</object>
</annotation>
